argrecord/__init__.py
argrecord/argrecord.py
argrecord/argreplay.py
argrecord/record.py
argrecord-0.1.3.dist-info/LICENSE
argrecord-0.1.3.dist-info/METADATA
argrecord-0.1.3.dist-info/WHEEL
argrecord-0.1.3.dist-info/entry_points.txt
argrecord-0.1.3.dist-info/top_level.txt
argrecord-0.1.3.dist-info/RECORD
