Metadata-Version: 2.1
Name: argrecord
Version: 0.1.3
Summary: Automates logfile and self-describing output file generation; provides Make-like functionality to re-run a script.
Author: Jonathan Schultz
Author-email: jonathan@schultz.la
License: GPL3
Classifier: Development Status :: 3 - Alpha
Classifier: License :: OSI Approved :: GNU General Public License v3 (GPLv3)
Classifier: Programming Language :: Python :: 3
Classifier: Intended Audience :: Developers
License-File: LICENSE
Requires-Dist: argparse
